odoo/addons/fieldservice_address_no_change/README.rst
odoo/addons/fieldservice_address_no_change/__init__.py
odoo/addons/fieldservice_address_no_change/__manifest__.py
odoo/addons/fieldservice_address_no_change/hooks.py
odoo/addons/fieldservice_address_no_change/i18n/es.po
odoo/addons/fieldservice_address_no_change/i18n/fieldservice_address_no_change.pot
odoo/addons/fieldservice_address_no_change/i18n/it.po
odoo/addons/fieldservice_address_no_change/models/__init__.py
odoo/addons/fieldservice_address_no_change/models/fsm_order.py
odoo/addons/fieldservice_address_no_change/readme/CONTRIBUTORS.md
odoo/addons/fieldservice_address_no_change/readme/DESCRIPTION.md
odoo/addons/fieldservice_address_no_change/readme/USAGE.md
odoo/addons/fieldservice_address_no_change/static/description/icon.png
odoo/addons/fieldservice_address_no_change/static/description/icon.svg
odoo/addons/fieldservice_address_no_change/static/description/index.html
odoo/addons/fieldservice_address_no_change/tests/__init__.py
odoo/addons/fieldservice_address_no_change/tests/test_historical_locations.py
odoo_addon_fieldservice_address_no_change-17.0.1.0.0.4.dist-info/METADATA
odoo_addon_fieldservice_address_no_change-17.0.1.0.0.4.dist-info/WHEEL
odoo_addon_fieldservice_address_no_change-17.0.1.0.0.4.dist-info/top_level.txt
odoo_addon_fieldservice_address_no_change-17.0.1.0.0.4.dist-info/RECORD
